{
    "adult": false,
    "backdrop_path": "/fQtt87hIJKdoqArVPGVdRzQuM5w.jpg",
    "created_by": [],
    "episode_run_time": [
        174
    ],
    "first_air_date": "2023-12-12",
    "genres": [
        {
            "id": 99,
            "name": "Documentary"
        }
    ],
    "homepage": "https://www.netflix.com/title/81697366",
    "id": 239243,
    "in_production": false,
    "languages": [
        "en"
    ],
    "last_air_date": "2023-12-12",
    "last_episode_to_air": {
        "id": 4910752,
        "name": "Episode 4",
        "overview": "Team USA prepares for an epic showdown against Sweden, which leads to an intense penalty shootout — and a devastating outcome in their World Cup journey.",
        "vote_average": 0,
        "vote_count": 0,
        "air_date": "2023-12-12",
        "episode_number": 4,
        "episode_type": "finale",
        "production_code": "",
        "runtime": 42,
        "season_number": 1,
        "show_id": 239243,
        "still_path": "/t2bs0CA7zDl4Xa98k4urZrQ3qRM.jpg"
    },
    "name": "Under Pressure: The U.S. Women's World Cup Team",
    "next_episode_to_air": null,
    "networks": [
        {
            "id": 213,
            "logo_path": "/wwemzKWzjKYJFfCeiB57q3r4Bcm.png",
            "name": "Netflix",
            "origin_country": ""
        }
    ],
    "number_of_episodes": 4,
    "number_of_seasons": 1,
    "origin_country": [
        "US"
    ],
    "original_language": "en",
    "original_name": "Under Pressure: The U.S. Women's World Cup Team",
    "overview": "In this docuseries, the U.S. women's national soccer team pursues their third consecutive title amid trials and triumphs at the 2023 FIFA World Cup.",
    "popularity": 17.067,
    "poster_path": "/arw7e6iw97KrBfyWjVbimWfxzl1.jpg",
    "production_companies": [
        {
            "id": 156093,
            "logo_path": "/t8POzVUpEWkennWeE4Jm7zDCQtL.png",
            "name": "TIME Studios",
            "origin_country": "US"
        },
        {
            "id": 158748,
            "logo_path": "/ng3lP36qnejNNBiYxUvSsCVC1sC.png",
            "name": "Words + Pictures",
            "origin_country": "US"
        },
        {
            "id": 214619,
            "logo_path": "/lCzwhDxSLwHS1sKgROkgzXcW1mW.png",
            "name": "FIFA",
            "origin_country": "CH"
        }
    ],
    "production_countries": [
        {
            "iso_3166_1": "US",
            "name": "United States of America"
        }
    ],
    "seasons": [
        {
            "air_date": "2023-12-12",
            "episode_count": 4,
            "id": 365188,
            "name": "Limited Series",
            "overview": "",
            "poster_path": null,
            "season_number": 1,
            "vote_average": 0
        }
    ],
    "spoken_languages": [
        {
            "english_name": "English",
            "iso_639_1": "en",
            "name": "English"
        }
    ],
    "status": "Ended",
    "tagline": "",
    "type": "Miniseries",
    "vote_average": 6.5,
    "vote_count": 2,
    "season_data": {
        "1": {
            "_id": "654eec6467b61300e5ddfb9f",
            "air_date": "2023-12-12",
            "episodes": [
                {
                    "air_date": "2023-12-12",
                    "episode_number": 1,
                    "episode_type": "standard",
                    "id": 4910749,
                    "name": "Episode 1",
                    "overview": "Ahead of the 2023 World Cup, the U.S. national team eyes a three-peat as veterans welcome new faces and hopefuls fight for coveted spots on the roster.",
                    "production_code": "",
                    "runtime": 45,
                    "season_number": 1,
                    "show_id": 239243,
                    "still_path": "/vo5DUITITwxzAqDH42jCf6Isobx.jpg",
                    "vote_average": 0,
                    "vote_count": 0,
                    "crew": [
                        {
                            "job": "Director",
                            "department": "Directing",
                            "credit_id": "654eed235a5ed0011e06d9ce",
                            "adult": false,
                            "gender": 1,
                            "id": 1640117,
                            "known_for_department": "Production",
                            "name": "Rebecca Gitlitz",
                            "original_name": "Rebecca Gitlitz",
                            "popularity": 0.6,
                            "profile_path": null
                        }
                    ],
                    "guest_stars": []
                },
                {
                    "air_date": "2023-12-12",
                    "episode_number": 2,
                    "episode_type": "standard",
                    "id": 4910750,
                    "name": "Episode 2",
                    "overview": "First-timers in the World Cup realize a childhood dream. The team is forced to adapt in challenging new ways. A star player makes a special announcement.",
                    "production_code": "",
                    "runtime": 45,
                    "season_number": 1,
                    "show_id": 239243,
                    "still_path": "/wnZCYvjM7jhigjuU42WdfelbCAA.jpg",
                    "vote_average": 0,
                    "vote_count": 0,
                    "crew": [
                        {
                            "job": "Director",
                            "department": "Directing",
                            "credit_id": "654eed235a5ed0011e06d9ce",
                            "adult": false,
                            "gender": 1,
                            "id": 1640117,
                            "known_for_department": "Production",
                            "name": "Rebecca Gitlitz",
                            "original_name": "Rebecca Gitlitz",
                            "popularity": 0.6,
                            "profile_path": null
                        }
                    ],
                    "guest_stars": []
                },
                {
                    "air_date": "2023-12-12",
                    "episode_number": 3,
                    "episode_type": "standard",
                    "id": 4910751,
                    "name": "Episode 3",
                    "overview": "With the tournament in motion, the team takes on the Netherlands and Portugal in the group-stage games, facing personal fears — and strong opponents.",
                    "production_code": "",
                    "runtime": 43,
                    "season_number": 1,
                    "show_id": 239243,
                    "still_path": "/v5S8f48O6HkinB7d3gBJjIQwy3U.jpg",
                    "vote_average": 0,
                    "vote_count": 0,
                    "crew": [
                        {
                            "job": "Director",
                            "department": "Directing",
                            "credit_id": "654eed235a5ed0011e06d9ce",
                            "adult": false,
                            "gender": 1,
                            "id": 1640117,
                            "known_for_department": "Production",
                            "name": "Rebecca Gitlitz",
                            "original_name": "Rebecca Gitlitz",
                            "popularity": 0.6,
                            "profile_path": null
                        }
                    ],
                    "guest_stars": []
                },
                {
                    "air_date": "2023-12-12",
                    "episode_number": 4,
                    "episode_type": "finale",
                    "id": 4910752,
                    "name": "Episode 4",
                    "overview": "Team USA prepares for an epic showdown against Sweden, which leads to an intense penalty shootout — and a devastating outcome in their World Cup journey.",
                    "production_code": "",
                    "runtime": 42,
                    "season_number": 1,
                    "show_id": 239243,
                    "still_path": "/t2bs0CA7zDl4Xa98k4urZrQ3qRM.jpg",
                    "vote_average": 0,
                    "vote_count": 0,
                    "crew": [
                        {
                            "job": "Director",
                            "department": "Directing",
                            "credit_id": "654eed235a5ed0011e06d9ce",
                            "adult": false,
                            "gender": 1,
                            "id": 1640117,
                            "known_for_department": "Production",
                            "name": "Rebecca Gitlitz",
                            "original_name": "Rebecca Gitlitz",
                            "popularity": 0.6,
                            "profile_path": null
                        }
                    ],
                    "guest_stars": []
                }
            ],
            "name": "Limited Series",
            "overview": "",
            "id": 365188,
            "poster_path": null,
            "season_number": 1,
            "vote_average": 0
        }
    }
}