{"adult":false,"backdrop_path":"/lCYGGbAKVBoHU64Y79okDG1rWz.jpg","created_by":[],"episode_run_time":[25],"first_air_date":"1996-04-02","genres":[{"id":16,"name":"Animation"}],"homepage":"","id":7407,"in_production":false,"languages":["en"],"last_air_date":"1998-05-07","last_episode_to_air":{"id":1297833,"name":"Monster Menace","overview":"","vote_average":0,"vote_count":0,"air_date":"1998-05-07","episode_number":13,"episode_type":"finale","production_code":"","runtime":25,"season_number":2,"show_id":7407,"still_path":null},"name":"Dennis the Menace and Gnasher","next_episode_to_air":null,"networks":[{"id":4,"logo_path":"/mVn7xESaTNmjBUyUtGNvDQd3CT1.png","name":"BBC One","origin_country":"GB"}],"number_of_episodes":26,"number_of_seasons":2,"origin_country":["GB"],"original_language":"en","original_name":"Dennis the Menace and Gnasher","overview":"Dennis and Gnasher is an animated British TV series based on characters from The Beano comic, It features the daily adventures of the rebellious schoolboy Dennis the Menace and his dog Gnasher.","popularity":8.508,"poster_path":"/d9lcuWdQNmQxnrw5ehAAUzOPtsO.jpg","production_companies":[{"id":88424,"logo_path":null,"name":"Beano Productions","origin_country":""},{"id":28159,"logo_path":"/vi4Y2pr4P7Yk38EjEuEm59ebaaU.png","name":"HiT Entertainment","origin_country":"GB"},{"id":3324,"logo_path":"/dqT3yOTlfJRmtvk52Ccd1O6dZ0A.png","name":"BBC","origin_country":"GB"}],"production_countries":[],"seasons":[{"air_date":"1996-04-02","episode_count":13,"id":75646,"name":"Season 1","overview":"","poster_path":null,"season_number":1,"vote_average":0},{"air_date":"1998-02-13","episode_count":13,"id":86864,"name":"Season 2","overview":"","poster_path":null,"season_number":2,"vote_average":0}],"spoken_languages":[{"english_name":"English","iso_639_1":"en","name":"English"}],"status":"Ended","tagline":"","type":"Scripted","vote_average":4.773,"vote_count":11,"season_data":{"1":{"_id":"56f375209251411a970018a1","air_date":"1996-04-02","episodes":[{"air_date":"1996-04-02","episode_number":1,"episode_type":"standard","id":1178451,"name":"Hair Today, Gone Tomorrow","overview":"","production_code":"","runtime":25,"season_number":1,"show_id":7407,"still_path":null,"vote_average":0,"vote_count":0,"crew":[],"guest_stars":[{"character":"Slasher Brown (voice)","credit_id":"58df8a80c3a3683d2a007592","order":500,"adult":false,"gender":2,"id":26663,"known_for_department":"Acting","name":"Denis Quilley","original_name":"Denis Quilley","popularity":2.387,"profile_path":"/n3A5eXkkqwatixxXuGp8IaZXSPc.jpg"}]},{"air_date":"1996-04-09","episode_number":2,"episode_type":"standard","id":1297805,"name":"The Day They Took Gnasher Away","overview":"","production_code":"","runtime":25,"season_number":1,"show_id":7407,"still_path":null,"vote_average":0,"vote_count":0,"crew":[],"guest_stars":[{"character":"Mr. Abercrombie (voice)","credit_id":"52578bf5760ee36aaa6881a8","order":6,"adult":false,"gender":2,"id":41419,"known_for_department":"Acting","name":"Hugh Laurie","original_name":"Hugh Laurie","popularity":27.97,"profile_path":"/akArncggHnusP5jxzMBKmJDRrMo.jpg"}]},{"air_date":"1996-04-16","episode_number":3,"episode_type":"standard","id":1297806,"name":"Bathnight Club","overview":"","production_code":"","runtime":25,"season_number":1,"show_id":7407,"still_path":null,"vote_average":0,"vote_count":0,"crew":[],"guest_stars":[]},{"air_date":"1996-04-23","episode_number":4,"episode_type":"standard","id":1297807,"name":"Dennis Ahoy!","overview":"","production_code":"","runtime":25,"season_number":1,"show_id":7407,"still_path":null,"vote_average":0,"vote_count":0,"crew":[],"guest_stars":[{"character":"Captain Trout (voice)","credit_id":"58df8aeb9251415e40007695","order":501,"adult":false,"gender":2,"id":9188,"known_for_department":"Acting","name":"Billy Connolly","original_name":"Billy Connolly","popularity":11.936,"profile_path":"/imqsEA1EPet7OvHx80VfTYfFcWf.jpg"}]},{"air_date":"1996-04-30","episode_number":5,"episode_type":"standard","id":1297808,"name":"Revenge of the Robot","overview":"","production_code":"","runtime":25,"season_number":1,"show_id":7407,"still_path":null,"vote_average":0,"vote_count":0,"crew":[],"guest_stars":[]},{"air_date":"1996-05-07","episode_number":6,"episode_type":"standard","id":1297809,"name":"Wanted!","overview":"","production_code":"","runtime":25,"season_number":1,"show_id":7407,"still_path":null,"vote_average":0,"vote_count":0,"crew":[],"guest_stars":[{"character":"Mr. Greenfly (voice)","credit_id":"58df8b389251415e44007f51","order":502,"adult":false,"gender":2,"id":10655,"known_for_department":"Acting","name":"Leslie Phillips","original_name":"Leslie Phillips","popularity":3.338,"profile_path":"/c46Qnx1QFEknR4pNWA2hTyDmrhA.jpg"}]},{"air_date":"1996-05-14","episode_number":7,"episode_type":"standard","id":1297810,"name":"Dennis and the Beanstalk","overview":"","production_code":"","runtime":25,"season_number":1,"show_id":7407,"still_path":null,"vote_average":0,"vote_count":0,"crew":[],"guest_stars":[]},{"air_date":"1996-05-21","episode_number":8,"episode_type":"standard","id":1297811,"name":"Unidentified Funny Object","overview":"","production_code":"","runtime":25,"season_number":1,"show_id":7407,"still_path":null,"vote_average":0,"vote_count":0,"crew":[],"guest_stars":[{"character":"Astronomer (voice)","credit_id":"58df8cc6c3a3683d2a0077b1","order":503,"adult":false,"gender":2,"id":29493,"known_for_department":"Acting","name":"Tim Brooke-Taylor","original_name":"Tim Brooke-Taylor","popularity":3.004,"profile_path":"/kKzfnLL7CEBdEL6eILZ8n0NDFgi.jpg"},{"character":"Astronomer (voice)","credit_id":"58df8cd99251415e3c007e38","order":504,"adult":false,"gender":2,"id":29492,"known_for_department":"Acting","name":"William Rushton","original_name":"William Rushton","popularity":1.886,"profile_path":"/fbZ74VUgcwUgzsSxq1KwCBuj4l1.jpg"}]},{"air_date":"1996-05-28","episode_number":9,"episode_type":"standard","id":1297812,"name":"Special Agent Dennis","overview":"","production_code":"","runtime":25,"season_number":1,"show_id":7407,"still_path":null,"vote_average":0,"vote_count":0,"crew":[],"guest_stars":[{"character":"Vilhemina Slop Bucket (voice)","credit_id":"58df8d089251415e7f007b79","order":505,"adult":false,"gender":1,"id":91721,"known_for_department":"Acting","name":"Mollie Sugden","original_name":"Mollie Sugden","popularity":4.364,"profile_path":"/pFshydzgVEaR2xz2As1Fnw7Gjf3.jpg"},{"character":"Muffin Man (voice)","credit_id":"58df8d19c3a3683d35007da2","order":506,"adult":false,"gender":2,"id":1225799,"known_for_department":"Acting","name":"Jonathan Kydd","original_name":"Jonathan Kydd","popularity":3.227,"profile_path":"/ycbubkCC4cy3ODEorsV0eHex8Pi.jpg"}]},{"air_date":"1996-06-04","episode_number":10,"episode_type":"standard","id":1297813,"name":"Dennis and the Grown-Ups","overview":"","production_code":"","runtime":25,"season_number":1,"show_id":7407,"still_path":null,"vote_average":0,"vote_count":0,"crew":[],"guest_stars":[{"character":"Mr. Smiley (voice)","credit_id":"58df8d609251415e400078bb","order":507,"adult":false,"gender":2,"id":94842,"known_for_department":"Acting","name":"Derek Nimmo","original_name":"Derek Nimmo","popularity":1.788,"profile_path":"/lH4iG8RKKBmKJvq38Y3BC3rojhh.jpg"}]},{"air_date":"1996-06-25","episode_number":11,"episode_type":"standard","id":1297814,"name":"The Secret Diary","overview":"","production_code":"","runtime":25,"season_number":1,"show_id":7407,"still_path":null,"vote_average":0,"vote_count":0,"crew":[],"guest_stars":[{"character":"Quentin Hitchberg (voice)","credit_id":"58df8df4c3a3683d2a00789d","order":508,"adult":false,"gender":2,"id":61965,"known_for_department":"Acting","name":"Greg Proops","original_name":"Greg Proops","popularity":2.81,"profile_path":"/t3ImKdWc9eJz29Y9aStQa8aFiRB.jpg"}]},{"air_date":"1996-07-02","episode_number":12,"episode_type":"standard","id":1297815,"name":"Gorilla Warfare","overview":"","production_code":"","runtime":25,"season_number":1,"show_id":7407,"still_path":null,"vote_average":0,"vote_count":0,"crew":[],"guest_stars":[]},{"air_date":"1996-07-09","episode_number":13,"episode_type":"finale","id":1297816,"name":"The Day TV Was Banned","overview":"","production_code":"","runtime":25,"season_number":1,"show_id":7407,"still_path":null,"vote_average":0,"vote_count":0,"crew":[],"guest_stars":[{"character":"Sir Fitz-Patrick Flush (voice)","credit_id":"58df8e41c3a3683d46007603","order":509,"adult":false,"gender":2,"id":202520,"known_for_department":"Acting","name":"Ken Dodd","original_name":"Ken Dodd","popularity":2.398,"profile_path":"/5QOoDSYJBZuETj5rB18mrIMQ0So.jpg"}]}],"name":"Season 1","overview":"","id":75646,"poster_path":null,"season_number":1,"vote_average":0},"2":{"_id":"58df920cc3a3683d2a007c76","air_date":"1998-02-13","episodes":[{"air_date":"1998-02-13","episode_number":1,"episode_type":"standard","id":1297821,"name":"The Competition!","overview":"Dennis and Walter enter a \"Blue Peter\" Competition.","production_code":"","runtime":25,"season_number":2,"show_id":7407,"still_path":null,"vote_average":0,"vote_count":0,"crew":[],"guest_stars":[{"character":"Herself (voice)","credit_id":"58df9acac3a3683d1e00860d","order":510,"adult":false,"gender":0,"id":1216379,"known_for_department":"Acting","name":"Katy Hill","original_name":"Katy Hill","popularity":0.6,"profile_path":null},{"character":"Himself (voice)","credit_id":"58df9ae1c3a3683d460080e7","order":511,"adult":false,"gender":0,"id":1787777,"known_for_department":"Acting","name":"Stuart Miles","original_name":"Stuart Miles","popularity":0.6,"profile_path":null}]},{"air_date":"1998-02-20","episode_number":2,"episode_type":"standard","id":1297822,"name":"Summer Holiday","overview":"","production_code":"","runtime":25,"season_number":2,"show_id":7407,"still_path":null,"vote_average":0,"vote_count":0,"crew":[],"guest_stars":[{"character":"Mrs. Duffel","credit_id":"58df9b479251415e6a008856","order":512,"adult":false,"gender":1,"id":55643,"known_for_department":"Acting","name":"Prunella Scales","original_name":"Prunella Scales","popularity":6.031,"profile_path":"/d4LgFFrAo3O5P8FxS5d6qg6bO1E.jpg"}]},{"air_date":"1998-02-27","episode_number":3,"episode_type":"standard","id":1297823,"name":"Menace Power","overview":"","production_code":"","runtime":25,"season_number":2,"show_id":7407,"still_path":null,"vote_average":0,"vote_count":0,"crew":[],"guest_stars":[]},{"air_date":"1998-03-06","episode_number":4,"episode_type":"standard","id":1297824,"name":"Dennisaurus Rex","overview":"","production_code":"","runtime":25,"season_number":2,"show_id":7407,"still_path":null,"vote_average":0,"vote_count":0,"crew":[],"guest_stars":[]},{"air_date":"1998-03-13","episode_number":5,"episode_type":"standard","id":1297825,"name":"Adventures in Dennis Sitting","overview":"","production_code":"","runtime":25,"season_number":2,"show_id":7407,"still_path":null,"vote_average":0,"vote_count":0,"crew":[],"guest_stars":[]},{"air_date":"1998-03-20","episode_number":6,"episode_type":"standard","id":1297826,"name":"Haunted House","overview":"","production_code":"","runtime":25,"season_number":2,"show_id":7407,"still_path":null,"vote_average":0,"vote_count":0,"crew":[],"guest_stars":[{"character":"Aunt Gertrude (voice)","credit_id":"58df9b93c3a3683d0b008478","order":513,"adult":false,"gender":0,"id":1787778,"known_for_department":"Acting","name":"Patrick Fyffe","original_name":"Patrick Fyffe","popularity":0.98,"profile_path":null},{"character":"Aunt Fanny (voice)","credit_id":"58df9bab9251415e7f0088e5","order":514,"adult":false,"gender":2,"id":1787779,"known_for_department":"Acting","name":"George Logan","original_name":"George Logan","popularity":0.742,"profile_path":null}]},{"air_date":"1998-03-27","episode_number":7,"episode_type":"standard","id":1297827,"name":"Oil Strike!","overview":"","production_code":"","runtime":25,"season_number":2,"show_id":7407,"still_path":null,"vote_average":0,"vote_count":0,"crew":[],"guest_stars":[{"character":"Katzenburger (voice)","credit_id":"58df9bc3c3a3683d0b008492","order":515,"adult":false,"gender":2,"id":40943,"known_for_department":"Acting","name":"Bernard Cribbins","original_name":"Bernard Cribbins","popularity":5.449,"profile_path":"/lLdaHLskigTNayxy4Tbrt7EKly2.jpg"}]},{"air_date":"1998-04-03","episode_number":8,"episode_type":"standard","id":1297828,"name":"Mauled","overview":"","production_code":"","runtime":25,"season_number":2,"show_id":7407,"still_path":null,"vote_average":0,"vote_count":0,"crew":[],"guest_stars":[]},{"air_date":"1998-04-09","episode_number":9,"episode_type":"standard","id":1297829,"name":"The Trial","overview":"","production_code":"","runtime":25,"season_number":2,"show_id":7407,"still_path":null,"vote_average":0,"vote_count":0,"crew":[],"guest_stars":[{"character":"Hugo Trenchfoot (voice)","credit_id":"58df9bea9251415e36008897","order":516,"adult":false,"gender":2,"id":4001,"known_for_department":"Acting","name":"Simon Callow","original_name":"Simon Callow","popularity":10.706,"profile_path":"/no6qlnMrWeUzSt1FjD2Vf9x992e.jpg"},{"character":"Finnigan (voice)","credit_id":"58df9bfb9251415e6a0088f9","order":517,"adult":false,"gender":2,"id":933883,"known_for_department":"Acting","name":"Eric Meyers","original_name":"Eric Meyers","popularity":0.621,"profile_path":null}]},{"air_date":"1998-04-16","episode_number":10,"episode_type":"standard","id":1297830,"name":"Journey to the Centre of the Bed","overview":"","production_code":"","runtime":25,"season_number":2,"show_id":7407,"still_path":null,"vote_average":0,"vote_count":0,"crew":[],"guest_stars":[{"character":"Captain (voice)","credit_id":"58df9c24c3a3683d2a0084b8","order":518,"adult":false,"gender":2,"id":8318,"known_for_department":"Acting","name":"Brian Blessed","original_name":"Brian Blessed","popularity":11.665,"profile_path":"/3mLIr94V5IOA5ndY6GyqKKcyrX6.jpg"}]},{"air_date":"1998-04-23","episode_number":11,"episode_type":"standard","id":1297831,"name":"Skull and Crossbones","overview":"","production_code":"","runtime":25,"season_number":2,"show_id":7407,"still_path":null,"vote_average":0,"vote_count":0,"crew":[],"guest_stars":[]},{"air_date":"1998-04-30","episode_number":12,"episode_type":"standard","id":1297832,"name":"Snowbound","overview":"","production_code":"","runtime":25,"season_number":2,"show_id":7407,"still_path":null,"vote_average":0,"vote_count":0,"crew":[],"guest_stars":[]},{"air_date":"1998-05-07","episode_number":13,"episode_type":"finale","id":1297833,"name":"Monster Menace","overview":"","production_code":"","runtime":25,"season_number":2,"show_id":7407,"still_path":null,"vote_average":0,"vote_count":0,"crew":[],"guest_stars":[{"character":"Jacques (voice)","credit_id":"58df9c4d9251415e5f008b3a","order":519,"adult":false,"gender":2,"id":141952,"known_for_department":"Acting","name":"Jimmy Hibbert","original_name":"Jimmy Hibbert","popularity":1.541,"profile_path":"/xTJRiJPVEfLDHBU8RSJVSFka6iQ.jpg"}]}],"name":"Season 2","overview":"","id":86864,"poster_path":null,"season_number":2,"vote_average":0}}}